CONTRIBUTING.rst
HISTORY.rst
LICENSE
MANIFEST.in
README.rst
setup.cfg
setup.py
bowa/__init__.py
bowa/bowa.py
bowa.egg-info/PKG-INFO
bowa.egg-info/SOURCES.txt
bowa.egg-info/dependency_links.txt
bowa.egg-info/not-zip-safe
bowa.egg-info/top_level.txt
docs/Makefile
docs/conf.py
docs/contributing.rst
docs/history.rst
docs/index.rst
docs/installation.rst
docs/make.bat
docs/readme.rst
docs/usage.rst
tests/test_bowa.py